PLANBERT/Engine.py
PLANBERT/Model.py
PLANBERT/__init__.py
PLANBERT/model/LossFunction.py
PLANBERT/model/PLANBERT.py
PLANBERT/model/__init__.py
PLANBERT/model/multihot_utils.py
PLANBERT/model/transformer_util/__init__.py
PLANBERT/model/transformer_util/attention.py
PLANBERT/model/transformer_util/bert.py
PLANBERT/model/transformer_util/extras.py
PLANBERT/model/transformer_util/lstm_models.py
PLANBERT/model/transformer_util/multihot_utils.py
PLANBERT/model/transformer_util/position.py
PLANBERT/model/transformer_util/transformer.py
PLANBERT/util/Datahelper.py
PLANBERT/util/Generator.py
PLANBERT/util/Metrics.py
PLANBERT/util/__init__.py
PLANBERT-1.3.dist-info/METADATA
PLANBERT-1.3.dist-info/WHEEL
PLANBERT-1.3.dist-info/top_level.txt
PLANBERT-1.3.dist-info/RECORD
