Metadata-Version: 2.1
Name: PLANBERT
Version: 1.3
Summary: A Bi-directional Transformer based sequential baskets recommender which incorporates future items
Home-page: https://github.com/CAHLR/PLAN-BERT
Author: Erzhuo Shao, Zachary A. Pardos
Author-email: shaoerzhuo@gmail.com, zp@berkeley.edu
License: MIT
Platform: UNKNOWN
Classifier: License :: OSI Approved :: MIT License
Classifier: Programming Language :: Python :: 3
Requires-Python: >=3.6.0
Requires-Dist: Keras (>=2.3.0)
Requires-Dist: numpy
Requires-Dist: pandas
Requires-Dist: tensorflow-gpu
Requires-Dist: tqdm
